onegram/__init__.py
onegram/account.py
onegram/aes.py
onegram/amount.py
onegram/asset.py
onegram/bitshares.py
onegram/block.py
onegram/blockchain.py
onegram/blockchainobject.py
onegram/committee.py
onegram/dex.py
onegram/exceptions.py
onegram/fee.py
onegram/instance.py
onegram/market.py
onegram/memo.py
onegram/message.py
onegram/notify.py
onegram/price.py
onegram/proposal.py
onegram/storage.py
onegram/transactionbuilder.py
onegram/utils.py
onegram/vesting.py
onegram/wallet.py
onegram/witness.py
onegram/worker.py
onegramapi/__init__.py
onegramapi/bitsharesnoderpc.py
onegramapi/exceptions.py
onegramapi/websocket.py
onegrambase/__init__.py
onegrambase/account.py
onegrambase/asset_permissions.py
onegrambase/bip38.py
onegrambase/chains.py
onegrambase/ecdsa.py
onegrambase/memo.py
onegrambase/objects.py
onegrambase/objecttypes.py
onegrambase/operationids.py
onegrambase/operations.py
onegrambase/signedtransactions.py
onegrambase/transactions.py
onegramcoin-1.0.5.dist-info/LICENSE.txt
onegramcoin-1.0.5.dist-info/METADATA
onegramcoin-1.0.5.dist-info/WHEEL
onegramcoin-1.0.5.dist-info/top_level.txt
onegramcoin-1.0.5.dist-info/zip-safe
onegramcoin-1.0.5.dist-info/RECORD
