Metadata-Version: 2.1
Name: onegramcoin
Version: 1.0.5
Summary: Python library for onegram
Home-page: https://gitlab.com/onegram-developers/python-onegram
Author: 01People
Author-email: info@01people.com
Maintainer: 01People
Maintainer-email: info@01people.com
License: UNKNOWN
Download-URL: https://gitlab.com/onegram-developers/python-onegram/-/archive/v1.0.5/python-onegram-v1.0.5.zip
Keywords: onegram,library,api,rpc
Platform: UNKNOWN
Classifier: License :: OSI Approved :: MIT License
Classifier: Operating System :: OS Independent
Classifier: Programming Language :: Python :: 3
Classifier: Development Status :: 3 - Alpha
Classifier: Intended Audience :: Developers
Classifier: Intended Audience :: Financial and Insurance Industry
Classifier: Topic :: Office/Business :: Financial
Requires-Dist: onegramlib (>=1.0.7)
Requires-Dist: websockets
Requires-Dist: appdirs
Requires-Dist: Events
Requires-Dist: scrypt
Requires-Dist: pycryptodome
